mlprogress/__init__.py
mlprogress/core.py
yhluprogress-0.1.0.dist-info/licenses/LICENSE
yhluprogress-0.1.0.dist-info/METADATA
yhluprogress-0.1.0.dist-info/WHEEL
yhluprogress-0.1.0.dist-info/top_level.txt
yhluprogress-0.1.0.dist-info/RECORD
